sng_parser/__init__.py
sng_parser/__main__.py
sng_parser/common.py
sng_parser/decode.py
sng_parser/encode.py
sng_parser-1.3.0.dist-info/LICENSE
sng_parser-1.3.0.dist-info/METADATA
sng_parser-1.3.0.dist-info/WHEEL
sng_parser-1.3.0.dist-info/entry_points.txt
sng_parser-1.3.0.dist-info/top_level.txt
sng_parser-1.3.0.dist-info/RECORD
