Metadata-Version: 2.1
Name: sng_parser
Version: 1.3.0
Summary: Python library for reading .sng files
Author-email: Josh Mcdaniel <80354972+joshrmcdaniel@users.noreply.github.com>
License: MIT License
Project-URL: homepage, https://github.com/joshrmcdaniel/sng-format-python
Keywords: sng,.sng,clone hero,ch,file,sng-format,sng-parse
Classifier: Development Status :: 5 - Production/Stable
Classifier: Intended Audience :: Developers
Classifier: License :: OSI Approved :: MIT License
Classifier: Programming Language :: Python :: 3.10
Classifier: Programming Language :: Python :: 3.11
Classifier: Programming Language :: Python :: 3.12
Requires-Python: >=3.10
License-File: LICENSE
Requires-Dist: soundfile ==0.12.1
Requires-Dist: cffi >=1.0
Requires-Dist: numpy
Provides-Extra: dev
Requires-Dist: scalene ; extra == 'dev'
